fabutils/__init__.py
fabutils/apt.py
fabutils/connections.py
fabutils/disks.py
fabutils/files.py
fabutils/locales.py
fabutils/postgresql.py
fabutils/services.py
fabutils/ssh.py
fabutils/ssl.py
fabutils/templates.py
fabutils/users.py
fabutils_cciw-0.1.1.dist-info/METADATA
fabutils_cciw-0.1.1.dist-info/WHEEL
fabutils_cciw-0.1.1.dist-info/top_level.txt
fabutils_cciw-0.1.1.dist-info/RECORD
